turtle_loc_oracles/__init__.py
turtle_loc_oracles/data/green_sea_turtle_swimming_coefficients.mat
turtle_loc_oracles/joint_space/__init__.py
turtle_loc_oracles/joint_space/biological_oracles.py
turtle_loc_oracles/joint_space/template_model_oracles.py
turtle_loc_oracles/task_space/__init__.py
turtle_loc_oracles/task_space/biological_oracles.py
turtle_loc_oracles-0.0.1.dist-info/LICENSE.txt
turtle_loc_oracles-0.0.1.dist-info/METADATA
turtle_loc_oracles-0.0.1.dist-info/WHEEL
turtle_loc_oracles-0.0.1.dist-info/top_level.txt
turtle_loc_oracles-0.0.1.dist-info/RECORD
