Metadata-Version: 2.1
Name: turtle-loc-oracles
Version: 0.0.1
Summary: Oracles for turtle locomotion (e.g., swimming, walking, etc.)
Author-email: Maximilian Stölzle <maximilian@stoelzle.ch>, "Zach J. Patterson" <zpatt@csail.mit.edu>
Maintainer-email: "Zach J. Patterson" <zpatt@csail.mit.edu>
License: MIT License
Project-URL: Homepage, https://github.com/crush-robotics/turtle-locomotion-oracles
Project-URL: Bug Reports, https://github.com/crush-robotics/turtle-locomotion-oracles/issues
Project-URL: Source, https://github.com/crush-robotics/turtle-locomotion-oracles/
Keywords: bioinspiration,robotics
Classifier: Development Status :: 3 - Alpha
Classifier: Intended Audience :: Developers
Classifier: Topic :: Software Development :: Build Tools
Classifier: License :: OSI Approved :: MIT License
Classifier: Programming Language :: Python :: 3
Classifier: Programming Language :: Python :: 3.10
Classifier: Programming Language :: Python :: 3.11
Classifier: Programming Language :: Python :: 3.12
Classifier: Programming Language :: Python :: 3.13
Classifier: Programming Language :: Python :: 3 :: Only
Requires-Python: >=3.10
License-File: LICENSE.txt
Requires-Dist: numpy
Requires-Dist: peppercorn
Requires-Dist: scipy
Provides-Extra: dev
Requires-Dist: check-manifest ; extra == 'dev'
Provides-Extra: test
Requires-Dist: coverage ; extra == 'test'
